repo2prompt/__init__.py
repo2prompt/extraction.py
repo2prompt/types.py
Repo2Prompt-0.1.2.dist-info/METADATA
Repo2Prompt-0.1.2.dist-info/WHEEL
Repo2Prompt-0.1.2.dist-info/top_level.txt
Repo2Prompt-0.1.2.dist-info/RECORD
