Metadata-Version: 2.1
Name: Repo2Prompt
Version: 0.1.2
Summary: Github repo -> prompt string
Home-page: https://github.com/yourusername/my_package
Author: Your Name
Author-email: your.email@example.com
Classifier: Programming Language :: Python :: 3
Classifier: License :: OSI Approved :: MIT License
Classifier: Operating System :: OS Independent
Requires-Python: >=3.6
Requires-Dist: requests >=2.20.0
Requires-Dist: tqdm >=4.60.0
Requires-Dist: aiohttp >=3.9.1
